asciipy/__init__.py
asciipy/cli.py
asciipy/palettes.py
asciipy/url_.py
asciipy_any-0.3.0.dist-info/LICENSE
asciipy_any-0.3.0.dist-info/METADATA
asciipy_any-0.3.0.dist-info/WHEEL
asciipy_any-0.3.0.dist-info/entry_points.txt
asciipy_any-0.3.0.dist-info/top_level.txt
asciipy_any-0.3.0.dist-info/RECORD
