Metadata-Version: 2.1
Name: asciipy-any
Version: 0.3.0
Summary: python library and cli tool to convert images and videos to ascii.
Home-page: https://github.com/anytarseir67/asciipy
Author: anytarseir67
License: GPLv3
Platform: UNKNOWN
License-File: LICENSE
Requires-Dist: Pillow
Requires-Dist: opencv-python
Requires-Dist: imageio
Provides-Extra: docs
Requires-Dist: sphinx ; extra == 'docs'
Requires-Dist: sphinxcontrib-trio ; extra == 'docs'
Requires-Dist: sphinxcontrib-websupport ; extra == 'docs'
Requires-Dist: typing-extensions ; extra == 'docs'
Requires-Dist: myst-parser ; extra == 'docs'
Provides-Extra: full
Requires-Dist: yt-dlp ; extra == 'full'
Requires-Dist: requests ; extra == 'full'
Provides-Extra: url
Requires-Dist: requests ; extra == 'url'
Provides-Extra: youtube
Requires-Dist: yt-dlp ; extra == 'youtube'
